<?xml version="1.0" encoding="UTF-8"?>
<mappings xmlns="http://dozermapper.github.io/schema/bean-mapping"
          xmlns:xsi="http://www.w3.org/2001/XMLSchema-instance"
          xsi:schemaLocation="http://dozermapper.github.io/schema/bean-mapping http://dozermapper.github.io/schema/bean-mapping.xsd">
    <mapping>
        <class-a>com.ez2pay.business.customer.CustomerDTO</class-a>
        <class-b>com.ez2pay.business.customer.Customer</class-b>
        <field>
            <a>customerFirstName</a>
            <b>firstName</b>
        </field>
        <field>
            <a>customerLastName</a>
            <b>lastName</b>
        </field>
        <field>
            <a>customerAddress</a>
            <b>address</b>
        </field>
        <field>
            <a>customerGender</a>
            <b>gender</b>
        </field>
        <field>
            <a>customerEmail</a>
            <b>email</b>
        </field>
    </mapping>

</mappings>